PMJPL/ECOv002-cal-val-PM-JPL-inputs.csv
PMJPL/ECOv002-cal-val-PM-JPL-outputs.csv
PMJPL/ECOv002-static-tower-PM-JPL-inputs.csv
PMJPL/ECOv002_calval_PMJPL_inputs.py
PMJPL/ECOv002_static_tower_PMJPL_inputs.py
PMJPL/PMJPL.py
PMJPL/PMJPL_parameter_from_IGBP.py
PMJPL/VPD_factor.py
PMJPL/__init__.py
PMJPL/calculate_gamma.py
PMJPL/canopy_aerodynamic_resistance.py
PMJPL/canopy_conductance.py
PMJPL/closed_minimum_temperature.py
PMJPL/closed_vapor_pressure_deficit.py
PMJPL/constants.py
PMJPL/correctance_factor.py
PMJPL/generate_PMJPL_inputs.py
PMJPL/interception.py
PMJPL/leaf_conductance_to_evaporated_water.py
PMJPL/leaf_conductance_to_sensible_heat.py
PMJPL/maximum_boundary_layer_resistance.py
PMJPL/minimum_boundary_layer_resistance.py
PMJPL/minimum_temperature_factor.py
PMJPL/mod16.csv
PMJPL/model.py
PMJPL/open_minimum_temperature.py
PMJPL/open_vapor_pressure_deficit.py
PMJPL/potential_soil_evaporation.py
PMJPL/potential_stomatal_conductance.py
PMJPL/process_PMJPL_table.py
PMJPL/process_daily_ET_table.py
PMJPL/soil_moisture_constraint.py
PMJPL/transpiration.py
PMJPL/verify.py
PMJPL/version.py
PMJPL/wet_canopy_resistance.py
PMJPL/wet_soil_evaporation.py
pm_jpl-1.8.0.dist-info/licenses/LICENSE
pm_jpl-1.8.0.dist-info/METADATA
pm_jpl-1.8.0.dist-info/WHEEL
pm_jpl-1.8.0.dist-info/top_level.txt
pm_jpl-1.8.0.dist-info/RECORD
