Metadata-Version: 2.4
Name: PM-JPL
Version: 1.8.0
Summary: JPL implementation of the MOD16 evapotranspiration algorithm for high resolution instantaneous remote sensing imagery
Author-email: Gregory Halverson <gregory.h.halverson@jpl.nasa.gov>, Qiaozhen Mu <qiaozhen@ntsg.umt.edu>, Maosheng Zhao <zhao@ntsg.umt.edu>, "Steven W. Running" <swr@ntsg.umt.edu>, "Claire S. Villanueva-Weeks" <claire.s.villanueva-weeks@jpl.gov>
Project-URL: Homepage, https://github.com/JPL-Evapotranspiration-Algorithms/PM-JPL
Classifier: Programming Language :: Python :: 3
Classifier: Operating System :: OS Independent
Requires-Python: >=3.10
License-File: LICENSE
Requires-Dist: carlson-fractional-vegetation-cover
Requires-Dist: carlson-leaf-area-index
Requires-Dist: check-distribution
Requires-Dist: daylight-evapotranspiration>=1.2.1
Requires-Dist: ECOv002-CMR>=1.0.5
Requires-Dist: ECOv002-granules>=1.0.3
Requires-Dist: ECOv003-granules
Requires-Dist: GEOS5FP>=1.1.1
Requires-Dist: MCD12C1_2019_v006
Requires-Dist: meteorology-conversion
Requires-Dist: NASADEM
Requires-Dist: numpy
Requires-Dist: pandas
Requires-Dist: priestley-taylor
Requires-Dist: PTJPL>=1.5.1
Requires-Dist: rasters>=1.11.0
Requires-Dist: SEBAL-soil-heat-flux
Requires-Dist: sun-angles>=1.3.0
Requires-Dist: verma-net-radiation>=1.8.0
Provides-Extra: dev
Requires-Dist: build; extra == "dev"
Requires-Dist: pytest>=6.0; extra == "dev"
Requires-Dist: pytest-cov; extra == "dev"
Requires-Dist: jupyter; extra == "dev"
Requires-Dist: pytest; extra == "dev"
Requires-Dist: twine; extra == "dev"
Dynamic: license-file
